cloudinary/__init__.py
cloudinary/api.py
cloudinary/auth_token.py
cloudinary/compat.py
cloudinary/exceptions.py
cloudinary/forms.py
cloudinary/http_client.py
cloudinary/models.py
cloudinary/search.py
cloudinary/search_folders.py
cloudinary/uploader.py
cloudinary/utils.py
cloudinary/api_client/__init__.py
cloudinary/api_client/call_account_api.py
cloudinary/api_client/call_api.py
cloudinary/api_client/execute_request.py
cloudinary/api_client/tcp_keep_alive_manager.py
cloudinary/cache/__init__.py
cloudinary/cache/responsive_breakpoints_cache.py
cloudinary/cache/adapter/__init__.py
cloudinary/cache/adapter/cache_adapter.py
cloudinary/cache/adapter/key_value_cache_adapter.py
cloudinary/cache/storage/__init__.py
cloudinary/cache/storage/file_system_key_value_storage.py
cloudinary/cache/storage/key_value_storage.py
cloudinary/poster/__init__.py
cloudinary/poster/encode.py
cloudinary/poster/streaminghttp.py
cloudinary/provisioning/__init__.py
cloudinary/provisioning/account.py
cloudinary/provisioning/account_config.py
cloudinary/static/cloudinary/html/cloudinary_cors.html
cloudinary/static/cloudinary/js/canvas-to-blob.min.js
cloudinary/static/cloudinary/js/jquery.cloudinary.js
cloudinary/static/cloudinary/js/jquery.fileupload-image.js
cloudinary/static/cloudinary/js/jquery.fileupload-process.js
cloudinary/static/cloudinary/js/jquery.fileupload-validate.js
cloudinary/static/cloudinary/js/jquery.fileupload.js
cloudinary/static/cloudinary/js/jquery.iframe-transport.js
cloudinary/static/cloudinary/js/jquery.ui.widget.js
cloudinary/static/cloudinary/js/load-image.all.min.js
cloudinary/templates/cloudinary_direct_upload.html
cloudinary/templates/cloudinary_includes.html
cloudinary/templates/cloudinary_js_config.html
cloudinary/templatetags/__init__.py
cloudinary/templatetags/cloudinary.py
cloudinary-1.44.1.dist-info/LICENSE.txt
cloudinary-1.44.1.dist-info/METADATA
cloudinary-1.44.1.dist-info/WHEEL
cloudinary-1.44.1.dist-info/top_level.txt
cloudinary-1.44.1.dist-info/RECORD
