Metadata-Version: 2.1
Name: cloudinary
Version: 1.44.1
Summary: Python and Django SDK for Cloudinary
Author-email: Cloudinary <info@cloudinary.com>
License: Released under the MIT license.
Project-URL: Homepage, https://cloudinary.com
Project-URL: Source, https://github.com/cloudinary/pycloudinary
Project-URL: Changelog, https://raw.githubusercontent.com/cloudinary/pycloudinary/master/CHANGELOG.md
Keywords: cloudinary,image,video,upload,crop,resize,filter,transformation,manipulation,cdn
Classifier: Development Status :: 5 - Production/Stable
Classifier: Environment :: Web Environment
Classifier: Framework :: Django
Classifier: Framework :: Django :: 1.11
Classifier: Framework :: Django :: 2.2
Classifier: Framework :: Django :: 3.2
Classifier: Framework :: Django :: 4.2
Classifier: Framework :: Django :: 5.0
Classifier: Framework :: Django :: 5.1
Classifier: Intended Audience :: Developers
Classifier: License :: OSI Approved :: MIT License
Classifier: Programming Language :: Python
Classifier: Programming Language :: Python :: 2
Classifier: Programming Language :: Python :: 2.7
Classifier: Programming Language :: Python :: 3
Classifier: Programming Language :: Python :: 3.9
Classifier: Programming Language :: Python :: 3.10
Classifier: Programming Language :: Python :: 3.11
Classifier: Programming Language :: Python :: 3.12
Classifier: Programming Language :: Python :: 3.13
Classifier: Topic :: Internet :: WWW/HTTP
Classifier: Topic :: Internet :: WWW/HTTP :: Dynamic Content
Classifier: Topic :: Multimedia :: Graphics
Classifier: Topic :: Multimedia :: Graphics :: Graphics Conversion
Classifier: Topic :: Multimedia :: Sound/Audio
Classifier: Topic :: Multimedia :: Sound/Audio :: Conversion
Classifier: Topic :: Multimedia :: Video
Classifier: Topic :: Multimedia :: Video :: Conversion
Classifier: Topic :: Software Development :: Libraries :: Python Modules
License-File: LICENSE.txt
Requires-Dist: six
Requires-Dist: urllib3>=1.26.5
Requires-Dist: certifi
Provides-Extra: dev
Requires-Dist: tox; extra == "dev"
Requires-Dist: pytest==4.6; python_version < "3.7" and extra == "dev"
Requires-Dist: pytest; python_version >= "3.7" and extra == "dev"
